nanozero/__init__.py
nanozero/alphazero.py
nanozero/utils.py
nanozero-0.1.0.dist-info/LICENSE
nanozero-0.1.0.dist-info/METADATA
nanozero-0.1.0.dist-info/WHEEL
nanozero-0.1.0.dist-info/top_level.txt
nanozero-0.1.0.dist-info/RECORD
