Metadata-Version: 2.1
Name: nanozero
Version: 0.1.0
Summary: NanoZero: An elegant single-file AlphaZero implementation scaling to thousands of parallel self-plays.
Author-email: Sotetsu KOYAMADA <sotetsu.koyamada@gmail.com>
Project-URL: Home, https://github.com/sotetsuk/nanozero
Project-URL: Documentation, https://github.com/sotetsuk/nanozero/README.md
Keywords: alphazero
License-File: LICENSE
Requires-Dist: pgx >=2.0.0
Requires-Dist: flax
